bbqec-1.4.dist-info/licenses/LICENSE
src/__init__.py
src/core.py
src/core_generalised.py
src/core_optimised.py
src/distances/__init__.py
src/distances/distance_from_bposd.py
src/distances/distance_from_brute_force.py
src/distances/distance_from_gap.py
src/distances/distance_from_generators.py
src/helpers/__init__.py
src/helpers/bivariates.py
src/helpers/graphs.py
src/helpers/group_helpers.py
src/helpers/linalg_helpers.py
src/helpers/parameters.py
src/helpers/polynomials.py
src/misc/__init__.py
src/misc/polynomials_extended.py
src/misc/validators.py
bbqec-1.4.dist-info/METADATA
bbqec-1.4.dist-info/WHEEL
bbqec-1.4.dist-info/top_level.txt
bbqec-1.4.dist-info/RECORD
