Metadata-Version: 2.4
Name: bbqec
Version: 1.4
Summary: A package for quantum error correction with bivariate bicycle codes
Home-page: https://github.com/vanshjjw/qec-bicycle-bivariate
Author: Vansh Jhunjhunwala
Author-email: vanshjh@gmail.com
Classifier: Programming Language :: Python :: 3
Classifier: License :: OSI Approved :: MIT License
Classifier: Operating System :: OS Independent
Classifier: Topic :: Scientific/Engineering :: Physics
Classifier: Intended Audience :: Science/Research
Requires-Python: >=3.8
License-File: LICENSE
Requires-Dist: ldpc==0.1.50
Requires-Dist: matplotlib==3.4.3
Requires-Dist: numpy==1.26.2
Requires-Dist: networkx==3.2.1
Requires-Dist: galois==0.4.1
Dynamic: author
Dynamic: author-email
Dynamic: classifier
Dynamic: description
Dynamic: description-content-type
Dynamic: home-page
Dynamic: license-file
Dynamic: requires-dist
Dynamic: requires-python
Dynamic: summary
